bert_embedding/__init__.py
bert_embedding/bert.py
bert_embedding/cli.py
bert_embedding/dataset.py
bert_embedding/version.py
bert_embedding/tests/__init__.py
bert_embedding/tests/test_bert.py
bert_embedding/tests/test_cli.py
bert_embedding-1.0.1.data/scripts/bert
bert_embedding-1.0.1.dist-info/LICENSE
bert_embedding-1.0.1.dist-info/METADATA
bert_embedding-1.0.1.dist-info/WHEEL
bert_embedding-1.0.1.dist-info/top_level.txt
bert_embedding-1.0.1.dist-info/RECORD
