Metadata-Version: 2.1
Name: bert-embedding
Version: 1.0.1
Summary: BERT token level embedding with MxNet
Home-page: https://github.com/imgarylai/bert_embedding
Author: Gary Lai
Author-email: gary@gary-lai.com
License: ALv2
Download-URL: https://github.com/imgarylai/bert_embedding/tree/master
Keywords: bert nlp mxnet gluonnlp machine deep learning sentence encoding embedding
Platform: UNKNOWN
Classifier: Development Status :: 3 - Alpha
Classifier: Intended Audience :: Science/Research
Classifier: Intended Audience :: Developers
Classifier: License :: OSI Approved :: Apache Software License
Classifier: Programming Language :: Python :: 3 :: Only
Classifier: Programming Language :: Python :: 3.4
Classifier: Programming Language :: Python :: 3.5
Classifier: Programming Language :: Python :: 3.6
Classifier: Topic :: Scientific/Engineering :: Artificial Intelligence
Classifier: Topic :: Scientific/Engineering :: Information Analysis
Classifier: Operating System :: POSIX
Classifier: Operating System :: Unix
Classifier: Operating System :: MacOS
Requires-Dist: typing (==3.6.6)
Requires-Dist: numpy (==1.14.6)
Requires-Dist: mxnet (==1.4.0)
Requires-Dist: gluonnlp (==0.6.0)
Provides-Extra: gpu
Requires-Dist: mxnet-cu92 (==1.3.0) ; extra == 'gpu'
